{
"meta":{"test_sets":[],"test_metrics":[],"learn_metrics":[{"best_value":"Min","name":"RMSE"}],"launch_mode":"Train","parameters":"","iteration_count":900,"learn_sets":["learn"],"name":"experiment"},
"iterations":[
{"learn":[1.650066967],"iteration":0,"passed_time":0.1011203003,"remaining_time":90.90714997},
{"learn":[1.606250335],"iteration":1,"passed_time":0.1912131315,"remaining_time":85.85469602},
{"learn":[1.566826927],"iteration":2,"passed_time":0.2729484792,"remaining_time":81.61159528},
{"learn":[1.531676088],"iteration":3,"passed_time":0.3721568616,"remaining_time":83.363137},
{"learn":[1.497607162],"iteration":4,"passed_time":0.4612161342,"remaining_time":82.55768803},
{"learn":[1.467076895],"iteration":5,"passed_time":0.5494916959,"remaining_time":81.87426269},
{"learn":[1.438272755],"iteration":6,"passed_time":0.6465287085,"remaining_time":82.47859095},
{"learn":[1.411214803],"iteration":7,"passed_time":0.7453244521,"remaining_time":83.10367641},
{"learn":[1.387048163],"iteration":8,"passed_time":0.833191546,"remaining_time":82.48596306},
{"learn":[1.364924679],"iteration":9,"passed_time":0.9152871684,"remaining_time":81.46055799},
{"learn":[1.345019695],"iteration":10,"passed_time":1.011723566,"remaining_time":81.76565911},
{"learn":[1.325386104],"iteration":11,"passed_time":1.095790398,"remaining_time":81.08848945},
{"learn":[1.307392473],"iteration":12,"passed_time":1.184545713,"remaining_time":80.82246516},
{"learn":[1.290814621],"iteration":13,"passed_time":1.275965986,"remaining_time":80.75041884},
{"learn":[1.275243963],"iteration":14,"passed_time":1.403473978,"remaining_time":82.8049647},
{"learn":[1.261679661],"iteration":15,"passed_time":1.493674253,"remaining_time":82.52550247},
{"learn":[1.249104444],"iteration":16,"passed_time":1.581279587,"remaining_time":82.13352208},
{"learn":[1.236292396],"iteration":17,"passed_time":1.665275512,"remaining_time":81.59850007},
{"learn":[1.226293975],"iteration":18,"passed_time":1.768066264,"remaining_time":81.98244098},
{"learn":[1.215081619],"iteration":19,"passed_time":1.849499151,"remaining_time":81.37796264},
{"learn":[1.204855288],"iteration":20,"passed_time":1.935427736,"remaining_time":81.01147522},
{"learn":[1.196409621],"iteration":21,"passed_time":2.02536243,"remaining_time":80.83037335},
{"learn":[1.18688039],"iteration":22,"passed_time":2.126970705,"remaining_time":81.10231774},
{"learn":[1.178678273],"iteration":23,"passed_time":2.221280924,"remaining_time":81.07675373},
{"learn":[1.170146387],"iteration":24,"passed_time":2.317917635,"remaining_time":81.12711723},
{"learn":[1.163181691],"iteration":25,"passed_time":2.423369492,"remaining_time":81.46249755},
{"learn":[1.156972409],"iteration":26,"passed_time":2.506889021,"remaining_time":81.05607833},
{"learn":[1.150888001],"iteration":27,"passed_time":2.59389135,"remaining_time":80.78118775},
{"learn":[1.145057961],"iteration":28,"passed_time":2.679573744,"remaining_time":80.4796114},
{"learn":[1.138737565],"iteration":29,"passed_time":2.765011372,"remaining_time":80.18532978},
{"learn":[1.131271841],"iteration":30,"passed_time":2.856001668,"remaining_time":80.06017578},
{"learn":[1.125700712],"iteration":31,"passed_time":2.9616035,"remaining_time":80.33349494},
{"learn":[1.121187894],"iteration":32,"passed_time":3.057290365,"remaining_time":80.32335595},
{"learn":[1.116463585],"iteration":33,"passed_time":3.14963166,"remaining_time":80.2229711},
{"learn":[1.111304061],"iteration":34,"passed_time":3.247075515,"remaining_time":80.249152},
{"learn":[1.107171389],"iteration":35,"passed_time":3.340095051,"remaining_time":80.16228124},
{"learn":[1.103345248],"iteration":36,"passed_time":3.438847414,"remaining_time":80.20879239},
{"learn":[1.09979866],"iteration":37,"passed_time":3.538869306,"remaining_time":80.27645637},
{"learn":[1.096451577],"iteration":38,"passed_time":3.63709798,"remaining_time":80.29593233},
{"learn":[1.092251527],"iteration":39,"passed_time":3.737163972,"remaining_time":80.34902541},
{"learn":[1.087929422],"iteration":40,"passed_time":3.853803273,"remaining_time":80.74187833},
{"learn":[1.084718819],"iteration":41,"passed_time":3.944957044,"remaining_time":80.58983675},
{"learn":[1.081651419],"iteration":42,"passed_time":4.033540276,"remaining_time":80.38939572},
{"learn":[1.078298776],"iteration":43,"passed_time":4.132174505,"remaining_time":80.38957674},
{"learn":[1.073911466],"iteration":44,"passed_time":4.232379385,"remaining_time":80.41520831},
{"learn":[1.070894494],"iteration":45,"passed_time":4.328603856,"remaining_time":80.36147158},
{"learn":[1.068427856],"iteration":46,"passed_time":4.426552819,"remaining_time":80.33722456},
{"learn":[1.066024099],"iteration":47,"passed_time":4.524605555,"remaining_time":80.31174861},
{"learn":[1.062846735],"iteration":48,"passed_time":4.625535014,"remaining_time":80.33327136},
{"learn":[1.06016209],"iteration":49,"passed_time":4.722194599,"remaining_time":80.27730819},
{"learn":[1.057453518],"iteration":50,"passed_time":4.819922135,"remaining_time":80.2375273},
{"learn":[1.055608106],"iteration":51,"passed_time":4.919284076,"remaining_time":80.22217109},
{"learn":[1.053475888],"iteration":52,"passed_time":5.014866543,"remaining_time":80.14324456},
{"learn":[1.050832707],"iteration":53,"passed_time":5.114324745,"remaining_time":80.12442101},
{"learn":[1.048483737],"iteration":54,"passed_time":5.211559816,"remaining_time":80.06850989},
{"learn":[1.046485612],"iteration":55,"passed_time":5.308854658,"remaining_time":80.01202377},
{"learn":[1.044617887],"iteration":56,"passed_time":5.408229454,"remaining_time":79.98486718},
{"learn":[1.042444119],"iteration":57,"passed_time":5.503806217,"remaining_time":79.90008335},
{"learn":[1.040865616],"iteration":58,"passed_time":5.603530436,"remaining_time":79.87405248},
{"learn":[1.039308401],"iteration":59,"passed_time":5.702303175,"remaining_time":79.83224446},
{"learn":[1.037327108],"iteration":60,"passed_time":5.805261095,"remaining_time":79.84613211},
{"learn":[1.035675388],"iteration":61,"passed_time":5.903718421,"remaining_time":79.79541994},
{"learn":[1.033074801],"iteration":62,"passed_time":5.989249764,"remaining_time":79.57146115},
{"learn":[1.030993786],"iteration":63,"passed_time":6.080818923,"remaining_time":79.43069718},
{"learn":[1.029117014],"iteration":64,"passed_time":6.175807518,"remaining_time":79.3353735},
{"learn":[1.027674621],"iteration":65,"passed_time":6.257669708,"remaining_time":79.07418994},
{"learn":[1.026124485],"iteration":66,"passed_time":6.347632412,"remaining_time":78.91907163},
{"learn":[1.023016315],"iteration":67,"passed_time":6.443535915,"remaining_time":78.83855708},
{"learn":[1.020201579],"iteration":68,"passed_time":6.542817709,"remaining_time":78.79828284},
{"learn":[1.018705221],"iteration":69,"passed_time":6.637853141,"remaining_time":78.70597296},
{"learn":[1.017058868],"iteration":70,"passed_time":6.763857239,"remaining_time":78.97517819},
{"learn":[1.015610151],"iteration":71,"passed_time":6.90818189,"remaining_time":79.44409173},
{"learn":[1.014228979],"iteration":72,"passed_time":7.069924551,"remaining_time":80.09352882},
{"learn":[1.012217082],"iteration":73,"passed_time":7.320931665,"remaining_time":81.71742643},
{"learn":[1.010856425],"iteration":74,"passed_time":7.652698091,"remaining_time":84.179679},
{"learn":[1.008862854],"iteration":75,"passed_time":7.932938575,"remaining_time":86.00975507},
{"learn":[1.007497825],"iteration":76,"passed_time":8.14314766,"remaining_time":87.03650032},
{"learn":[1.006247291],"iteration":77,"passed_time":8.396027072,"remaining_time":88.48120837},
{"learn":[1.004883266],"iteration":78,"passed_time":8.639104181,"remaining_time":89.78107003},
{"learn":[1.002959639],"iteration":79,"passed_time":8.893798761,"remaining_time":91.1614373},
{"learn":[1.001455544],"iteration":80,"passed_time":9.15052125,"remaining_time":92.52193708},
{"learn":[0.9995475373],"iteration":81,"passed_time":9.357571839,"remaining_time":93.34748493},
{"learn":[0.998193056],"iteration":82,"passed_time":9.601823064,"remaining_time":94.51433064},
{"learn":[0.9968279549],"iteration":83,"passed_time":9.870914009,"remaining_time":95.88887894},
{"learn":[0.9957131602],"iteration":84,"passed_time":10.11552376,"remaining_time":96.99002195},
{"learn":[0.9935084884],"iteration":85,"passed_time":10.36534568,"remaining_time":98.1092021},
{"learn":[0.9913935889],"iteration":86,"passed_time":10.63075513,"remaining_time":99.34257379},
{"learn":[0.9904214456],"iteration":87,"passed_time":10.88216955,"remaining_time":100.4127463},
{"learn":[0.9888731435],"iteration":88,"passed_time":11.10787105,"remaining_time":101.2189148},
{"learn":[0.9878112674],"iteration":89,"passed_time":11.38220481,"remaining_time":102.4398433},
{"learn":[0.9864817751],"iteration":90,"passed_time":11.62706413,"remaining_time":103.3658778},
{"learn":[0.9853919504],"iteration":91,"passed_time":11.85597583,"remaining_time":104.1263964},
{"learn":[0.9841975587],"iteration":92,"passed_time":12.08321887,"remaining_time":104.8511573},
{"learn":[0.9829386915],"iteration":93,"passed_time":12.33893411,"remaining_time":105.7997968},
{"learn":[0.9819594158],"iteration":94,"passed_time":12.57583952,"remaining_time":106.5636927},
{"learn":[0.9809356042],"iteration":95,"passed_time":12.80902949,"remaining_time":107.275622},
{"learn":[0.9796333929],"iteration":96,"passed_time":13.03894025,"remaining_time":107.9409177},
{"learn":[0.9775870918],"iteration":97,"passed_time":13.2723738,"remaining_time":108.6167733},
{"learn":[0.9765933075],"iteration":98,"passed_time":13.5069682,"remaining_time":109.2836518},
{"learn":[0.9754460311],"iteration":99,"passed_time":13.7534076,"remaining_time":110.0272608},
{"learn":[0.9746396922],"iteration":100,"passed_time":14.00270237,"remaining_time":110.7738534},
{"learn":[0.973576245],"iteration":101,"passed_time":14.22998376,"remaining_time":111.3286965},
{"learn":[0.9726511537],"iteration":102,"passed_time":14.48927383,"remaining_time":112.1160315},
{"learn":[0.971749807],"iteration":103,"passed_time":14.73993846,"remaining_time":112.8172213},
{"learn":[0.9698303596],"iteration":104,"passed_time":14.98196446,"remaining_time":113.4348738},
{"learn":[0.9688144986],"iteration":105,"passed_time":15.20073957,"remaining_time":113.8621435},
{"learn":[0.9678542561],"iteration":106,"passed_time":15.42695452,"remaining_time":114.332476},
{"learn":[0.9656973086],"iteration":107,"passed_time":15.67000665,"remaining_time":114.9133821},
{"learn":[0.964894195],"iteration":108,"passed_time":15.93205373,"remaining_time":115.6170138},
{"learn":[0.9631527729],"iteration":109,"passed_time":16.17766221,"remaining_time":116.1850286},
{"learn":[0.9620022595],"iteration":110,"passed_time":16.39605826,"remaining_time":116.5449547},
{"learn":[0.961189763],"iteration":111,"passed_time":16.6220347,"remaining_time":116.947887},
{"learn":[0.9602833731],"iteration":112,"passed_time":16.88101637,"remaining_time":117.5695565},
{"learn":[0.9591951761],"iteration":113,"passed_time":17.09800396,"remaining_time":117.8862378},
{"learn":[0.9582068303],"iteration":114,"passed_time":17.32327954,"remaining_time":118.2502125},
{"learn":[0.9570974753],"iteration":115,"passed_time":17.58358929,"remaining_time":118.8408104},
{"learn":[0.9564496311],"iteration":116,"passed_time":17.81262776,"remaining_time":119.2075858},
{"learn":[0.9550530612],"iteration":117,"passed_time":18.03862663,"remaining_time":119.5441189},
{"learn":[0.9538671386],"iteration":118,"passed_time":18.29867216,"remaining_time":120.0946467},
{"learn":[0.9530879206],"iteration":119,"passed_time":18.5411652,"remaining_time":120.5175738},
{"learn":[0.9519817821],"iteration":120,"passed_time":18.77083504,"remaining_time":120.8469462},
{"learn":[0.9508810434],"iteration":121,"passed_time":18.99562791,"remaining_time":121.1360534},
{"learn":[0.9491862659],"iteration":122,"passed_time":19.24164447,"remaining_time":121.550876},
{"learn":[0.9484271186],"iteration":123,"passed_time":19.49535375,"remaining_time":122.0031815},
{"learn":[0.9471160685],"iteration":124,"passed_time":19.73411566,"remaining_time":122.3515171},
{"learn":[0.9463637695],"iteration":125,"passed_time":19.95513248,"remaining_time":122.5815281},
{"learn":[0.9447218122],"iteration":126,"passed_time":20.15651237,"remaining_time":122.6849139},
{"learn":[0.9440106922],"iteration":127,"passed_time":20.41149948,"remaining_time":123.1068562},
{"learn":[0.94243562],"iteration":128,"passed_time":20.68543825,"remaining_time":123.6315728},
{"learn":[0.9407197442],"iteration":129,"passed_time":20.92105317,"remaining_time":123.9170072},
{"learn":[0.9396700848],"iteration":130,"passed_time":21.13815744,"remaining_time":124.085825},
{"learn":[0.9383039824],"iteration":131,"passed_time":21.36693679,"remaining_time":124.3167232},
{"learn":[0.9376469836],"iteration":132,"passed_time":21.5829817,"remaining_time":124.4672704},
{"learn":[0.9368348508],"iteration":133,"passed_time":21.81939475,"remaining_time":124.7287789},
{"learn":[0.9358954736],"iteration":134,"passed_time":22.06904492,"remaining_time":125.0579212},
{"learn":[0.9349528197],"iteration":135,"passed_time":22.31996295,"remaining_time":125.3856742},
{"learn":[0.9322780423],"iteration":136,"passed_time":22.59055727,"remaining_time":125.8145635},
{"learn":[0.9317644919],"iteration":137,"passed_time":22.83167975,"remaining_time":126.0705795},
{"learn":[0.9299399782],"iteration":138,"passed_time":23.05518746,"remaining_time":126.2230047},
{"learn":[0.9293410375],"iteration":139,"passed_time":23.30957644,"remaining_time":126.5377007},
{"learn":[0.9286860119],"iteration":140,"passed_time":23.55990131,"remaining_time":126.8224475},
{"learn":[0.9276636107],"iteration":141,"passed_time":23.79349205,"remaining_time":127.0103308},
{"learn":[0.9258363677],"iteration":142,"passed_time":24.05585002,"remaining_time":127.3446047},
{"learn":[0.925137071],"iteration":143,"passed_time":24.2932306,"remaining_time":127.5394607},
{"learn":[0.9244430628],"iteration":144,"passed_time":24.51517675,"remaining_time":127.6479893},
{"learn":[0.9231715583],"iteration":145,"passed_time":24.75528635,"remaining_time":127.8457939},
{"learn":[0.922566423],"iteration":146,"passed_time":25.00580833,"remaining_time":128.0909774},
{"learn":[0.9217100616],"iteration":147,"passed_time":25.24853687,"remaining_time":128.289863},
{"learn":[0.9203668078],"iteration":148,"passed_time":25.48778332,"remaining_time":128.4652703},
{"learn":[0.9194031853],"iteration":149,"passed_time":25.72008947,"remaining_time":128.6004474},
{"learn":[0.9184876966],"iteration":150,"passed_time":25.95691441,"remaining_time":128.7531715},
{"learn":[0.9175558159],"iteration":151,"passed_time":26.1903431,"remaining_time":128.8840568},
{"learn":[0.9167248307],"iteration":152,"passed_time":26.41904106,"remaining_time":128.9870828},
{"learn":[0.9161509426],"iteration":153,"passed_time":26.63604233,"remaining_time":129.0291401},
{"learn":[0.9154191354],"iteration":154,"passed_time":26.86669112,"remaining_time":129.1334509},
{"learn":[0.9139656032],"iteration":155,"passed_time":27.08288603,"remaining_time":129.1645334},
{"learn":[0.9127446749],"iteration":156,"passed_time":27.31908885,"remaining_time":129.287153},
{"learn":[0.9122480554],"iteration":157,"passed_time":27.60461028,"remaining_time":129.6368407},
{"learn":[0.9115832178],"iteration":158,"passed_time":27.84688306,"remaining_time":129.7769833},
{"learn":[0.9108690977],"iteration":159,"passed_time":28.08940223,"remaining_time":129.9134853},
{"learn":[0.9102894519],"iteration":160,"passed_time":28.31975099,"remaining_time":129.989416},
{"learn":[0.9096054117],"iteration":161,"passed_time":28.57203116,"remaining_time":130.1614753},
{"learn":[0.9087977883],"iteration":162,"passed_time":28.8115697,"remaining_time":130.270717},
{"learn":[0.9079122324],"iteration":163,"passed_time":29.06259379,"remaining_time":130.4272502},
{"learn":[0.9064963201],"iteration":164,"passed_time":29.3039759,"remaining_time":130.5358927},
{"learn":[0.9058374929],"iteration":165,"passed_time":29.56902816,"remaining_time":130.7449799},
{"learn":[0.9051595684],"iteration":166,"passed_time":29.81087864,"remaining_time":130.8465511},
{"learn":[0.9043577097],"iteration":167,"passed_time":30.06026171,"remaining_time":130.9768546},
{"learn":[0.9035959815],"iteration":168,"passed_time":30.3229188,"remaining_time":131.1600807},
{"learn":[0.9022222039],"iteration":169,"passed_time":30.56033103,"remaining_time":131.2296568},
{"learn":[0.9008437161],"iteration":170,"passed_time":30.79039783,"remaining_time":131.2643276},
{"learn":[0.8997227268],"iteration":171,"passed_time":30.99814688,"remaining_time":131.2014589},
{"learn":[0.8988147122],"iteration":172,"passed_time":31.24056424,"remaining_time":131.2826023},
{"learn":[0.8981140775],"iteration":173,"passed_time":31.510188,"remaining_time":131.4735431},
{"learn":[0.8974353931],"iteration":174,"passed_time":31.75005204,"remaining_time":131.5359299},
{"learn":[0.8969359436],"iteration":175,"passed_time":32.02760291,"remaining_time":131.749912},
{"learn":[0.8957550536],"iteration":176,"passed_time":32.29121321,"remaining_time":131.9013963},
{"learn":[0.8952681513],"iteration":177,"passed_time":32.54446352,"remaining_time":132.0061947},
{"learn":[0.8944587586],"iteration":178,"passed_time":32.79731634,"remaining_time":132.1053915},
{"learn":[0.893739781],"iteration":179,"passed_time":33.04514055,"remaining_time":132.1805622},
{"learn":[0.8924256655],"iteration":180,"passed_time":33.27614621,"remaining_time":132.1853543},
{"learn":[0.8917295361],"iteration":181,"passed_time":33.49412769,"remaining_time":132.1361741},
{"learn":[0.8907899919],"iteration":182,"passed_time":33.72346073,"remaining_time":132.1296248},
{"learn":[0.8897923553],"iteration":183,"passed_time":34.0129118,"remaining_time":132.3545916},
{"learn":[0.8890562959],"iteration":184,"passed_time":34.25798802,"remaining_time":132.4024942},
{"learn":[0.887453401],"iteration":185,"passed_time":34.51308377,"remaining_time":132.4857087},
{"learn":[0.8854882539],"iteration":186,"passed_time":34.75778715,"remaining_time":132.5256804},
{"learn":[0.8849182801],"iteration":187,"passed_time":35.00292112,"remaining_time":132.5642545},
{"learn":[0.8843494548],"iteration":188,"passed_time":35.24462461,"remaining_time":132.5869212},
{"learn":[0.8827443889],"iteration":189,"passed_time":35.49480994,"remaining_time":132.6385003},
{"learn":[0.8822956223],"iteration":190,"passed_time":35.70695855,"remaining_time":132.5457257},
{"learn":[0.8818624874],"iteration":191,"passed_time":35.92162138,"remaining_time":132.4609789},
{"learn":[0.8810461251],"iteration":192,"passed_time":36.1703052,"remaining_time":132.4995118},
{"learn":[0.8804709657],"iteration":193,"passed_time":36.44641696,"remaining_time":132.6348988},
{"learn":[0.8794624809],"iteration":194,"passed_time":36.69330546,"remaining_time":132.6604121},
{"learn":[0.8790452764],"iteration":195,"passed_time":36.93185382,"remaining_time":132.6531892},
{"learn":[0.8785590743],"iteration":196,"passed_time":37.16378749,"remaining_time":132.6200132},
{"learn":[0.877957256],"iteration":197,"passed_time":37.42030933,"remaining_time":132.6720058},
{"learn":[0.87755264],"iteration":198,"passed_time":37.67132916,"remaining_time":132.7015163},
{"learn":[0.8771346452],"iteration":199,"passed_time":37.87405671,"remaining_time":132.5591985},
{"learn":[0.8767215373],"iteration":200,"passed_time":38.10455702,"remaining_time":132.5128625},
{"learn":[0.8761645379],"iteration":201,"passed_time":38.327707,"remaining_time":132.4393044},
{"learn":[0.8754514322],"iteration":202,"passed_time":38.56436589,"remaining_time":132.4106553},
{"learn":[0.8748791238],"iteration":203,"passed_time":38.78288689,"remaining_time":132.3180847},
{"learn":[0.8743703955],"iteration":204,"passed_time":38.9750252,"remaining_time":132.1348415},
{"learn":[0.8739395514],"iteration":205,"passed_time":39.18327738,"remaining_time":132.0057985},
{"learn":[0.87348289],"iteration":206,"passed_time":39.38050062,"remaining_time":131.8390673},
{"learn":[0.8726641435],"iteration":207,"passed_time":39.57258002,"remaining_time":131.6549297},
{"learn":[0.8722600138],"iteration":208,"passed_time":39.81871212,"remaining_time":131.6494262},
{"learn":[0.8713200693],"iteration":209,"passed_time":40.0268801,"remaining_time":131.5168917},
{"learn":[0.8707938674],"iteration":210,"passed_time":40.22195794,"remaining_time":131.3408958},
{"learn":[0.8704764675],"iteration":211,"passed_time":40.4319882,"remaining_time":131.2132447},
{"learn":[0.8700783136],"iteration":212,"passed_time":40.6382804,"remaining_time":131.0727635},
{"learn":[0.8692968595],"iteration":213,"passed_time":40.824226,"remaining_time":130.8664441},
{"learn":[0.8684540506],"iteration":214,"passed_time":41.01403912,"remaining_time":130.6726363},
{"learn":[0.8677204058],"iteration":215,"passed_time":41.21121653,"remaining_time":130.5021857},
{"learn":[0.8673434502],"iteration":216,"passed_time":41.41520488,"remaining_time":130.352926},
{"learn":[0.8666494261],"iteration":217,"passed_time":41.62880239,"remaining_time":130.2332258},
{"learn":[0.8659990286],"iteration":218,"passed_time":41.84830803,"remaining_time":130.13104},
{"learn":[0.8656521135],"iteration":219,"passed_time":42.0452045,"remaining_time":129.9579048},
{"learn":[0.8652833179],"iteration":220,"passed_time":42.24463294,"remaining_time":129.7923338},
{"learn":[0.8647532119],"iteration":221,"passed_time":42.45829257,"remaining_time":129.6699205},
{"learn":[0.8641729188],"iteration":222,"passed_time":42.65350516,"remaining_time":129.4906861},
{"learn":[0.8633874703],"iteration":223,"passed_time":42.8840026,"remaining_time":129.4177936},
{"learn":[0.8629607835],"iteration":224,"passed_time":43.06210951,"remaining_time":129.1863285},
{"learn":[0.8619064086],"iteration":225,"passed_time":43.24775633,"remaining_time":128.977822},
{"learn":[0.8607182126],"iteration":226,"passed_time":43.43693015,"remaining_time":128.7799735},
{"learn":[0.8602870226],"iteration":227,"passed_time":43.65496198,"remaining_time":128.6672564},
{"learn":[0.859904134],"iteration":228,"passed_time":43.87183014,"remaining_time":128.5502097},
{"learn":[0.8594964787],"iteration":229,"passed_time":44.06268811,"remaining_time":128.3565262},
{"learn":[0.8591231189],"iteration":230,"passed_time":44.27460044,"remaining_time":128.2238428},
{"learn":[0.8586101055],"iteration":231,"passed_time":44.48496967,"remaining_time":128.0860334},
{"learn":[0.8581256641],"iteration":232,"passed_time":44.68502529,"remaining_time":127.9180767},
{"learn":[0.8571693838],"iteration":233,"passed_time":44.89092079,"remaining_time":127.7664669},
{"learn":[0.8568529034],"iteration":234,"passed_time":45.10209842,"remaining_time":127.6293423},
{"learn":[0.8563891974],"iteration":235,"passed_time":45.32132507,"remaining_time":127.5142366},
{"learn":[0.8555578014],"iteration":236,"passed_time":45.53055288,"remaining_time":127.3702808},
{"learn":[0.8550441702],"iteration":237,"passed_time":45.75084621,"remaining_time":127.2565554},
{"learn":[0.8541069874],"iteration":238,"passed_time":45.97093152,"remaining_time":127.1413629},
{"learn":[0.8534636468],"iteration":239,"passed_time":46.21294309,"remaining_time":127.0855935},
{"learn":[0.8531040358],"iteration":240,"passed_time":46.41959711,"remaining_time":126.9315954},
{"learn":[0.8527105066],"iteration":241,"passed_time":46.61958825,"remaining_time":126.7590457},
{"learn":[0.8518791811],"iteration":242,"passed_time":46.84094239,"remaining_time":126.6440294},
{"learn":[0.8515470331],"iteration":243,"passed_time":47.03272536,"remaining_time":126.4486387},
{"learn":[0.8511951188],"iteration":244,"passed_time":47.23626181,"remaining_time":126.2846999},
{"learn":[0.8506457911],"iteration":245,"passed_time":47.42938644,"remaining_time":126.0927591},
{"learn":[0.8501433773],"iteration":246,"passed_time":47.62717953,"remaining_time":125.9131508},
{"learn":[0.8493314002],"iteration":247,"passed_time":47.85401085,"remaining_time":125.8097382},
{"learn":[0.8489747294],"iteration":248,"passed_time":48.07871995,"remaining_time":125.6997859},
{"learn":[0.8486536112],"iteration":249,"passed_time":48.26183111,"remaining_time":125.4807609},
{"learn":[0.8482092068],"iteration":250,"passed_time":48.46506669,"remaining_time":125.3140569},
{"learn":[0.847871575],"iteration":251,"passed_time":48.66148776,"remaining_time":125.1295399},
{"learn":[0.8475549605],"iteration":252,"passed_time":48.8674238,"remaining_time":124.9692617},
{"learn":[0.8470809865],"iteration":253,"passed_time":49.06666019,"remaining_time":124.7915846},
{"learn":[0.846728363],"iteration":254,"passed_time":49.30163092,"remaining_time":124.7041253},
{"learn":[0.8459535686],"iteration":255,"passed_time":49.50045468,"remaining_time":124.5245813},
{"learn":[0.8450509047],"iteration":256,"passed_time":49.69448717,"remaining_time":124.3328998},
{"learn":[0.8447797999],"iteration":257,"passed_time":49.9015906,"remaining_time":124.1737255},
{"learn":[0.8443329481],"iteration":258,"passed_time":50.10558569,"remaining_time":124.0064881},
{"learn":[0.8437456201],"iteration":259,"passed_time":50.3228173,"remaining_time":123.8715503},
{"learn":[0.8430051426],"iteration":260,"passed_time":50.50483141,"remaining_time":123.6497597},
{"learn":[0.842320406],"iteration":261,"passed_time":50.70916193,"remaining_time":123.4826157},
{"learn":[0.8417259322],"iteration":262,"passed_time":50.92368077,"remaining_time":123.3398656},
{"learn":[0.841387844],"iteration":263,"passed_time":51.1315901,"remaining_time":123.1806489},
{"learn":[0.8407863062],"iteration":264,"passed_time":51.34591186,"remaining_time":123.0364303},
{"learn":[0.8402407407],"iteration":265,"passed_time":51.54811557,"remaining_time":122.8628018},
{"learn":[0.8396736483],"iteration":266,"passed_time":51.72817306,"remaining_time":122.6364552},
{"learn":[0.8392132889],"iteration":267,"passed_time":51.92403163,"remaining_time":122.4477164},
{"learn":[0.8386752785],"iteration":268,"passed_time":52.17022012,"remaining_time":122.3769848},
{"learn":[0.838181454],"iteration":269,"passed_time":52.39037001,"remaining_time":122.2441967},
{"learn":[0.8375871972],"iteration":270,"passed_time":52.59452298,"remaining_time":122.0736345},
{"learn":[0.837221324],"iteration":271,"passed_time":52.80292751,"remaining_time":121.9126414},
{"learn":[0.8369192987],"iteration":272,"passed_time":53.03327119,"remaining_time":121.8016888},
{"learn":[0.8362159803],"iteration":273,"passed_time":53.23886841,"remaining_time":121.6333271},
{"learn":[0.8358684497],"iteration":274,"passed_time":53.44806358,"remaining_time":121.4728718},
{"learn":[0.835004857],"iteration":275,"passed_time":53.66383821,"remaining_time":121.3269386},
{"learn":[0.8346981499],"iteration":276,"passed_time":53.85128269,"remaining_time":121.1167838},
{"learn":[0.8340901698],"iteration":277,"passed_time":54.08327122,"remaining_time":121.0064557},
{"learn":[0.8338323713],"iteration":278,"passed_time":54.49316528,"remaining_time":121.2912388},
{"learn":[0.8332790843],"iteration":279,"passed_time":54.74071228,"remaining_time":121.2115772},
{"learn":[0.8328191353],"iteration":280,"passed_time":54.96488153,"remaining_time":121.079223},
{"learn":[0.8321302534],"iteration":281,"passed_time":55.16130576,"remaining_time":120.8854148},
{"learn":[0.8317136373],"iteration":282,"passed_time":55.37683362,"remaining_time":120.733238},
{"learn":[0.8312181965],"iteration":283,"passed_time":55.56961414,"remaining_time":120.5312757},
{"learn":[0.8307171749],"iteration":284,"passed_time":55.78543553,"remaining_time":120.3790977},
{"learn":[0.8301576353],"iteration":285,"passed_time":55.97834636,"remaining_time":120.177289},
{"learn":[0.829624846],"iteration":286,"passed_time":56.19295373,"remaining_time":120.0218838},
{"learn":[0.8289143366],"iteration":287,"passed_time":56.3907701,"remaining_time":119.8303865},
{"learn":[0.8285743618],"iteration":288,"passed_time":56.66369604,"remaining_time":119.7976411},
{"learn":[0.828087459],"iteration":289,"passed_time":56.92826746,"remaining_time":119.745666},
{"learn":[0.8278216942],"iteration":290,"passed_time":57.14860688,"remaining_time":119.5996618},
{"learn":[0.8270859978],"iteration":291,"passed_time":57.37512573,"remaining_time":119.4660152},
{"learn":[0.8268858824],"iteration":292,"passed_time":57.59530463,"remaining_time":119.3186004},
{"learn":[0.8265386176],"iteration":293,"passed_time":57.8144586,"remaining_time":119.1685779},
{"learn":[0.8263020687],"iteration":294,"passed_time":58.04493571,"remaining_time":119.0413088},
{"learn":[0.8258165878],"iteration":295,"passed_time":58.26683107,"remaining_time":118.895831},
{"learn":[0.8254411136],"iteration":296,"passed_time":58.49287459,"remaining_time":118.7582605},
{"learn":[0.8250806018],"iteration":297,"passed_time":58.7321461,"remaining_time":118.6468186},
{"learn":[0.824439094],"iteration":298,"passed_time":58.96104261,"remaining_time":118.5136676},
{"learn":[0.8239000477],"iteration":299,"passed_time":59.21403033,"remaining_time":118.4280607},
{"learn":[0.8235526223],"iteration":300,"passed_time":59.46584592,"remaining_time":118.339009},
{"learn":[0.8232080062],"iteration":301,"passed_time":59.67014226,"remaining_time":118.154785},
{"learn":[0.8227387403],"iteration":302,"passed_time":59.89137918,"remaining_time":118.0038065},
{"learn":[0.8223698606],"iteration":303,"passed_time":60.11401136,"remaining_time":117.8551012},
{"learn":[0.8220684668],"iteration":304,"passed_time":60.34729665,"remaining_time":117.7266935},
{"learn":[0.8217364091],"iteration":305,"passed_time":60.57954217,"remaining_time":117.5955819},
{"learn":[0.8212809475],"iteration":306,"passed_time":60.81826034,"remaining_time":117.476314},
{"learn":[0.8210473373],"iteration":307,"passed_time":61.05946269,"remaining_time":117.3610452},
{"learn":[0.8206184334],"iteration":308,"passed_time":61.28331269,"remaining_time":117.2117728},
{"learn":[0.820241631],"iteration":309,"passed_time":61.50825387,"remaining_time":117.0640961},
{"learn":[0.8197505341],"iteration":310,"passed_time":61.74384681,"remaining_time":116.9360957},
{"learn":[0.8194520792],"iteration":311,"passed_time":61.98284816,"remaining_time":116.8138292},
{"learn":[0.8191153876],"iteration":312,"passed_time":62.20614376,"remaining_time":116.6613623},
{"learn":[0.8188537422],"iteration":313,"passed_time":62.44359137,"remaining_time":116.5348552},
{"learn":[0.8186018104],"iteration":314,"passed_time":62.66111928,"remaining_time":116.3706501},
{"learn":[0.8181329742],"iteration":315,"passed_time":62.88803959,"remaining_time":116.2234656},
{"learn":[0.8176957453],"iteration":316,"passed_time":63.11941426,"remaining_time":116.0839701},
{"learn":[0.8173132848],"iteration":317,"passed_time":63.35379444,"remaining_time":115.9493974},
{"learn":[0.8171039466],"iteration":318,"passed_time":63.60736001,"remaining_time":115.8491416},
{"learn":[0.816605897],"iteration":319,"passed_time":63.81326034,"remaining_time":115.6615344},
{"learn":[0.8160976669],"iteration":320,"passed_time":64.07106004,"remaining_time":115.567426},
{"learn":[0.8156735937],"iteration":321,"passed_time":64.30699993,"remaining_time":115.433062},
{"learn":[0.8152286237],"iteration":322,"passed_time":64.53150592,"remaining_time":115.2776437},
{"learn":[0.8147944465],"iteration":323,"passed_time":64.76912425,"remaining_time":115.1451098},
{"learn":[0.8141305488],"iteration":324,"passed_time":64.99841132,"remaining_time":114.9971893},
{"learn":[0.8135051167],"iteration":325,"passed_time":65.22640858,"remaining_time":114.8464985},
{"learn":[0.8132269593],"iteration":326,"passed_time":65.50888639,"remaining_time":114.7908009},
{"learn":[0.8129184233],"iteration":327,"passed_time":65.7124216,"remaining_time":114.5960523},
{"learn":[0.812634492],"iteration":328,"passed_time":65.96086059,"remaining_time":114.4791836},
{"learn":[0.8123038399],"iteration":329,"passed_time":66.18078622,"remaining_time":114.3122671},
{"learn":[0.8118059813],"iteration":330,"passed_time":66.38222817,"remaining_time":114.1132563},
{"learn":[0.8113779409],"iteration":331,"passed_time":66.62083502,"remaining_time":113.9778141},
{"learn":[0.8111146477],"iteration":332,"passed_time":66.85892743,"remaining_time":113.8408764},
{"learn":[0.8108458361],"iteration":333,"passed_time":67.0838486,"remaining_time":113.6810129},
{"learn":[0.8103680639],"iteration":334,"passed_time":67.31792231,"remaining_time":113.5361973},
{"learn":[0.8096434937],"iteration":335,"passed_time":67.53583483,"remaining_time":113.3637228},
{"learn":[0.8092675159],"iteration":336,"passed_time":67.78482907,"remaining_time":113.2429044},
{"learn":[0.8088410579],"iteration":337,"passed_time":68.01117454,"remaining_time":113.0836689},
{"learn":[0.8084764219],"iteration":338,"passed_time":68.24238054,"remaining_time":112.9320811},
{"learn":[0.808084574],"iteration":339,"passed_time":68.49774866,"remaining_time":112.8198213},
{"learn":[0.8076919261],"iteration":340,"passed_time":68.74255524,"remaining_time":112.6894087},
{"learn":[0.8073493526],"iteration":341,"passed_time":68.96117116,"remaining_time":112.515595},
{"learn":[0.8071379207],"iteration":342,"passed_time":69.21717084,"remaining_time":112.4022279},
{"learn":[0.8069071936],"iteration":343,"passed_time":69.46112825,"remaining_time":112.2685678},
{"learn":[0.8065707891],"iteration":344,"passed_time":69.68194309,"remaining_time":112.0970389},
{"learn":[0.8061588823],"iteration":345,"passed_time":69.91562788,"remaining_time":111.9458319},
{"learn":[0.805617958],"iteration":346,"passed_time":70.13232473,"remaining_time":111.7670766},
{"learn":[0.8051271805],"iteration":347,"passed_time":70.37846058,"remaining_time":111.6347995},
{"learn":[0.8046766075],"iteration":348,"passed_time":70.59345416,"remaining_time":111.4527027},
{"learn":[0.8042852287],"iteration":349,"passed_time":70.82357238,"remaining_time":111.2941852},
{"learn":[0.8040036387],"iteration":350,"passed_time":71.06772799,"remaining_time":111.1572156},
{"learn":[0.8036712524],"iteration":351,"passed_time":71.30018192,"remaining_time":111.0014196},
{"learn":[0.8033251754],"iteration":352,"passed_time":71.51745821,"remaining_time":110.8216704},
{"learn":[0.8030484061],"iteration":353,"passed_time":71.7349777,"remaining_time":110.6420842},
{"learn":[0.802497278],"iteration":354,"passed_time":71.93946132,"remaining_time":110.4422716},
{"learn":[0.8022173419],"iteration":355,"passed_time":72.14625423,"remaining_time":110.2459615},
{"learn":[0.8019061732],"iteration":356,"passed_time":72.36582891,"remaining_time":110.0690339},
{"learn":[0.801670948],"iteration":357,"passed_time":72.59381768,"remaining_time":109.9046067},
{"learn":[0.8008233866],"iteration":358,"passed_time":72.80004006,"remaining_time":109.7070242},
{"learn":[0.8005600975],"iteration":359,"passed_time":73.00885453,"remaining_time":109.5132818},
{"learn":[0.7999072829],"iteration":360,"passed_time":73.23965486,"remaining_time":109.3522825},
{"learn":[0.7994848603],"iteration":361,"passed_time":73.43318838,"remaining_time":109.135512},
{"learn":[0.799206965],"iteration":362,"passed_time":73.61306479,"remaining_time":108.8986661},
{"learn":[0.7987019827],"iteration":363,"passed_time":73.82523426,"remaining_time":108.7096856},
{"learn":[0.7984677433],"iteration":364,"passed_time":74.05673045,"remaining_time":108.5489063},
{"learn":[0.7978207449],"iteration":365,"passed_time":74.28160901,"remaining_time":108.3780853},
{"learn":[0.7976180281],"iteration":366,"passed_time":74.50517193,"remaining_time":108.205059},
{"learn":[0.7972873503],"iteration":367,"passed_time":74.75266763,"remaining_time":108.0663565},
{"learn":[0.7969845561],"iteration":368,"passed_time":74.98306001,"remaining_time":107.9024522},
{"learn":[0.7966663921],"iteration":369,"passed_time":75.20975894,"remaining_time":107.7328979},
{"learn":[0.7964096171],"iteration":370,"passed_time":75.43461609,"remaining_time":107.5604095},
{"learn":[0.7960005954],"iteration":371,"passed_time":75.64916312,"remaining_time":107.3730057},
{"learn":[0.7957186994],"iteration":372,"passed_time":75.8758422,"remaining_time":107.2025974},
{"learn":[0.7954875987],"iteration":373,"passed_time":76.10996524,"remaining_time":107.0423575},
{"learn":[0.7950565262],"iteration":374,"passed_time":76.31916631,"remaining_time":106.8468328},
{"learn":[0.7946378685],"iteration":375,"passed_time":76.51379427,"remaining_time":106.6309261},
{"learn":[0.7943769282],"iteration":376,"passed_time":76.72822966,"remaining_time":106.4426104},
{"learn":[0.7941851885],"iteration":377,"passed_time":76.92517986,"remaining_time":106.2300103},
{"learn":[0.7938047269],"iteration":378,"passed_time":77.1260155,"remaining_time":106.022834},
{"learn":[0.7935035776],"iteration":379,"passed_time":77.33577901,"remaining_time":105.8279081},
{"learn":[0.7932449264],"iteration":380,"passed_time":77.54159051,"remaining_time":105.6275209},
{"learn":[0.7927947574],"iteration":381,"passed_time":77.75695273,"remaining_time":105.4400563},
{"learn":[0.7924907312],"iteration":382,"passed_time":77.9769339,"remaining_time":105.258681},
{"learn":[0.7921203295],"iteration":383,"passed_time":78.20394358,"remaining_time":105.0865492},
{"learn":[0.7918765204],"iteration":384,"passed_time":78.41841788,"remaining_time":104.8973642},
{"learn":[0.7915017424],"iteration":385,"passed_time":78.62053225,"remaining_time":104.6915896},
{"learn":[0.7912177519],"iteration":386,"passed_time":78.81010207,"remaining_time":104.4692051},
{"learn":[0.790983171],"iteration":387,"passed_time":79.00347374,"remaining_time":104.2520066},
{"learn":[0.7906443143],"iteration":388,"passed_time":79.200339,"remaining_time":104.0395199},
{"learn":[0.7903494772],"iteration":389,"passed_time":79.41674975,"remaining_time":103.8526728},
{"learn":[0.7900067391],"iteration":390,"passed_time":79.60717522,"remaining_time":103.631847},
{"learn":[0.7897640283],"iteration":391,"passed_time":79.83360102,"remaining_time":103.4578299},
{"learn":[0.7893678893],"iteration":392,"passed_time":80.01896464,"remaining_time":103.2305727},
{"learn":[0.789103188],"iteration":393,"passed_time":80.21683676,"remaining_time":103.0195924},
{"learn":[0.7885579111],"iteration":394,"passed_time":80.42310936,"remaining_time":102.8194183},
{"learn":[0.7882777358],"iteration":395,"passed_time":80.61770165,"remaining_time":102.6043476},
{"learn":[0.7879315352],"iteration":396,"passed_time":80.81625702,"remaining_time":102.3944012},
{"learn":[0.7876156387],"iteration":397,"passed_time":81.03197957,"remaining_time":102.2061652},
{"learn":[0.787412155],"iteration":398,"passed_time":81.21602085,"remaining_time":101.9780111},
{"learn":[0.7870106337],"iteration":399,"passed_time":81.41975905,"remaining_time":101.7746988},
{"learn":[0.7866291796],"iteration":400,"passed_time":81.60967388,"remaining_time":101.5541827},
{"learn":[0.7864442879],"iteration":401,"passed_time":81.80646829,"remaining_time":101.3423413},
{"learn":[0.7862576288],"iteration":402,"passed_time":82.0025062,"remaining_time":101.1296416},
{"learn":[0.7860267958],"iteration":403,"passed_time":82.22205549,"remaining_time":100.9458899},
{"learn":[0.7856774289],"iteration":404,"passed_time":82.43839208,"remaining_time":100.7580348},
{"learn":[0.7853913146],"iteration":405,"passed_time":82.6481437,"remaining_time":100.5620271},
{"learn":[0.7851276854],"iteration":406,"passed_time":82.84862321,"remaining_time":100.3547205},
{"learn":[0.7848913698],"iteration":407,"passed_time":83.05209108,"remaining_time":100.151051},
{"learn":[0.7845580504],"iteration":408,"passed_time":83.25993509,"remaining_time":99.95263601},
{"learn":[0.7843124119],"iteration":409,"passed_time":83.46586401,"remaining_time":99.75188625},
{"learn":[0.7839305138],"iteration":410,"passed_time":83.68033673,"remaining_time":99.56127655},
{"learn":[0.7837625871],"iteration":411,"passed_time":83.86811032,"remaining_time":99.33892679},
{"learn":[0.7834747326],"iteration":412,"passed_time":84.07713544,"remaining_time":99.14180378},
{"learn":[0.7832575097],"iteration":413,"passed_time":84.26567387,"remaining_time":98.92057367},
{"learn":[0.7829263929],"iteration":414,"passed_time":84.45410274,"remaining_time":98.69937309},
{"learn":[0.7826319297],"iteration":415,"passed_time":84.67161167,"remaining_time":98.51216358},
{"learn":[0.78232692],"iteration":416,"passed_time":84.93793659,"remaining_time":98.38135102},
{"learn":[0.7820370701],"iteration":417,"passed_time":85.13417084,"remaining_time":98.16906781},
{"learn":[0.7817206714],"iteration":418,"passed_time":85.36288157,"remaining_time":97.99414329},
{"learn":[0.7814077659],"iteration":419,"passed_time":85.56784086,"remaining_time":97.79181813},
{"learn":[0.7811448558],"iteration":420,"passed_time":85.77138403,"remaining_time":97.58786924},
{"learn":[0.7808037442],"iteration":421,"passed_time":85.98207999,"remaining_time":97.39202425},
{"learn":[0.7805060871],"iteration":422,"passed_time":86.17517118,"remaining_time":97.17625687},
{"learn":[0.7803225932],"iteration":423,"passed_time":86.38366926,"remaining_time":96.97789285},
{"learn":[0.7799849523],"iteration":424,"passed_time":86.58056645,"remaining_time":96.76651545},
{"learn":[0.779728209],"iteration":425,"passed_time":86.81395871,"remaining_time":96.59581321},
{"learn":[0.779522088],"iteration":426,"passed_time":87.02646751,"remaining_time":96.40168415},
{"learn":[0.7792541316],"iteration":427,"passed_time":87.25042796,"remaining_time":96.22009812},
{"learn":[0.7789703834],"iteration":428,"passed_time":87.45762268,"remaining_time":96.01990742},
{"learn":[0.7785131025],"iteration":429,"passed_time":87.67959701,"remaining_time":95.83583859},
{"learn":[0.7782796469],"iteration":430,"passed_time":87.88588796,"remaining_time":95.63452773},
{"learn":[0.7779866115],"iteration":431,"passed_time":88.11964493,"remaining_time":95.46294867},
{"learn":[0.7777526629],"iteration":432,"passed_time":88.37162801,"remaining_time":95.31073968},
{"learn":[0.777514509],"iteration":433,"passed_time":88.70811144,"remaining_time":95.24880168},
{"learn":[0.777258405],"iteration":434,"passed_time":88.9729795,"remaining_time":95.10904705},
{"learn":[0.7770256986],"iteration":435,"passed_time":89.20974715,"remaining_time":94.93881348},
{"learn":[0.776645165],"iteration":436,"passed_time":89.44315325,"remaining_time":94.76471386},
{"learn":[0.7763713777],"iteration":437,"passed_time":89.67760301,"remaining_time":94.59144428},
{"learn":[0.7761148785],"iteration":438,"passed_time":89.92641189,"remaining_time":94.43297468},
{"learn":[0.7759663171],"iteration":439,"passed_time":90.15297784,"remaining_time":94.25084047},
{"learn":[0.7757562284],"iteration":440,"passed_time":90.39378281,"remaining_time":94.08332496},
{"learn":[0.7755324609],"iteration":441,"passed_time":90.65416658,"remaining_time":93.93576538},
{"learn":[0.775236545],"iteration":442,"passed_time":90.90896811,"remaining_time":93.78193776},
{"learn":[0.7749368714],"iteration":443,"passed_time":91.14795546,"remaining_time":93.61141371},
{"learn":[0.7745752041],"iteration":444,"passed_time":91.36803411,"remaining_time":93.42124836},
{"learn":[0.774363689],"iteration":445,"passed_time":91.60142503,"remaining_time":93.24449991},
{"learn":[0.7741548736],"iteration":446,"passed_time":91.83702843,"remaining_time":93.06974022},
{"learn":[0.7738925547],"iteration":447,"passed_time":92.0810419,"remaining_time":92.90319406},
{"learn":[0.7736414494],"iteration":448,"passed_time":92.32557314,"remaining_time":92.73682291},
{"learn":[0.7731827018],"iteration":449,"passed_time":92.5758334,"remaining_time":92.5758334},
{"learn":[0.7729235849],"iteration":450,"passed_time":92.80842049,"remaining_time":92.39685322},
{"learn":[0.7726768635],"iteration":451,"passed_time":93.04396333,"remaining_time":92.22056543},
{"learn":[0.7723335125],"iteration":452,"passed_time":93.28515245,"remaining_time":92.04958751},
{"learn":[0.7720707789],"iteration":453,"passed_time":93.52611209,"remaining_time":91.87807487},
{"learn":[0.7717983329],"iteration":454,"passed_time":93.77178475,"remaining_time":91.7108664},
{"learn":[0.7715895462],"iteration":455,"passed_time":94.02340654,"remaining_time":91.54910637},
{"learn":[0.7714081283],"iteration":456,"passed_time":94.29302076,"remaining_time":91.4043943},
{"learn":[0.7712330593],"iteration":457,"passed_time":94.55211422,"remaining_time":91.24898359},
{"learn":[0.7710700248],"iteration":458,"passed_time":94.79751273,"remaining_time":91.07996321},
{"learn":[0.7708121955],"iteration":459,"passed_time":95.01788771,"remaining_time":90.8866752},
{"learn":[0.7705020304],"iteration":460,"passed_time":95.27260499,"remaining_time":90.72597308},
{"learn":[0.7701814347],"iteration":461,"passed_time":95.55092372,"remaining_time":90.58723937},
{"learn":[0.7698612932],"iteration":462,"passed_time":95.80753648,"remaining_time":90.42741564},
{"learn":[0.7696857028],"iteration":463,"passed_time":96.03996284,"remaining_time":90.24444784},
{"learn":[0.7693983936],"iteration":464,"passed_time":96.28679763,"remaining_time":90.07474617},
{"learn":[0.7691241154],"iteration":465,"passed_time":96.52121112,"remaining_time":89.89314512},
{"learn":[0.7687110605],"iteration":466,"passed_time":96.73466398,"remaining_time":89.6918833},
{"learn":[0.7685494105],"iteration":467,"passed_time":96.96064839,"remaining_time":89.50213698},
{"learn":[0.768375611],"iteration":468,"passed_time":97.17887747,"remaining_time":89.30510915},
{"learn":[0.7681689787],"iteration":469,"passed_time":97.42055028,"remaining_time":89.12943962},
{"learn":[0.7679131753],"iteration":470,"passed_time":97.63328575,"remaining_time":88.92713288},
{"learn":[0.7675656757],"iteration":471,"passed_time":97.88469526,"remaining_time":88.75985079},
{"learn":[0.767382029],"iteration":472,"passed_time":98.12843604,"remaining_time":88.58529004},
{"learn":[0.7668598512],"iteration":473,"passed_time":98.38230776,"remaining_time":88.41954242},
{"learn":[0.7666298188],"iteration":474,"passed_time":98.61265848,"remaining_time":88.23237864},
{"learn":[0.7664485923],"iteration":475,"passed_time":98.82724071,"remaining_time":88.03098752},
{"learn":[0.766244742],"iteration":476,"passed_time":99.01772216,"remaining_time":87.80816871},
{"learn":[0.7660755882],"iteration":477,"passed_time":99.23941472,"remaining_time":87.61303977},
{"learn":[0.765871817],"iteration":478,"passed_time":99.47704785,"remaining_time":87.43181032},
{"learn":[0.7656966963],"iteration":479,"passed_time":99.74849257,"remaining_time":87.279931},
{"learn":[0.7654230468],"iteration":480,"passed_time":100.0271521,"remaining_time":87.13383935},
{"learn":[0.7651608667],"iteration":481,"passed_time":100.2921109,"remaining_time":86.97531606},
{"learn":[0.7648903513],"iteration":482,"passed_time":100.5268203,"remaining_time":86.79023615},
{"learn":[0.7645579654],"iteration":483,"passed_time":100.803399,"remaining_time":86.64093794},
{"learn":[0.7643127982],"iteration":484,"passed_time":101.0648757,"remaining_time":86.47819257},
{"learn":[0.764125309],"iteration":485,"passed_time":101.3141385,"remaining_time":86.30463653},
{"learn":[0.7639329047],"iteration":486,"passed_time":101.5596359,"remaining_time":86.12757623},
{"learn":[0.7637599697],"iteration":487,"passed_time":101.8190558,"remaining_time":85.96198976},
{"learn":[0.7635630141],"iteration":488,"passed_time":102.0962835,"remaining_time":85.81098675},
{"learn":[0.7633192812],"iteration":489,"passed_time":102.3370979,"remaining_time":85.62900025},
{"learn":[0.7631365184],"iteration":490,"passed_time":102.5954057,"remaining_time":85.46134608},
{"learn":[0.7629575323],"iteration":491,"passed_time":102.8271949,"remaining_time":85.27133234},
{"learn":[0.7626999248],"iteration":492,"passed_time":103.0720365,"remaining_time":85.09192464},
{"learn":[0.762504553],"iteration":493,"passed_time":103.3472937,"remaining_time":84.93724945},
{"learn":[0.7623148317],"iteration":494,"passed_time":103.5529843,"remaining_time":84.72516898},
{"learn":[0.7620673707],"iteration":495,"passed_time":103.8012047,"remaining_time":84.54775548},
{"learn":[0.7619024178],"iteration":496,"passed_time":104.0327014,"remaining_time":84.35649633},
{"learn":[0.7617097862],"iteration":497,"passed_time":104.2839594,"remaining_time":84.18102748},
{"learn":[0.7614655966],"iteration":498,"passed_time":104.547245,"remaining_time":84.01492037},
{"learn":[0.7612484319],"iteration":499,"passed_time":104.7784776,"remaining_time":83.82278209},
{"learn":[0.7609755815],"iteration":500,"passed_time":105.0059502,"remaining_time":83.6274933},
{"learn":[0.7607156824],"iteration":501,"passed_time":105.2360945,"remaining_time":83.43419448},
{"learn":[0.7605060332],"iteration":502,"passed_time":105.4826896,"remaining_time":83.25373317},
{"learn":[0.7602527661],"iteration":503,"passed_time":105.7268583,"remaining_time":83.07110298},
{"learn":[0.7600486441],"iteration":504,"passed_time":105.9250988,"remaining_time":82.85230503},
{"learn":[0.7597491855],"iteration":505,"passed_time":106.198996,"remaining_time":82.69249888},
{"learn":[0.7595787334],"iteration":506,"passed_time":106.4360891,"remaining_time":82.50371402},
{"learn":[0.7594487562],"iteration":507,"passed_time":106.6573533,"remaining_time":82.30252456},
{"learn":[0.7592268935],"iteration":508,"passed_time":106.8938616,"remaining_time":82.1129664},
{"learn":[0.7588839025],"iteration":509,"passed_time":107.1662069,"remaining_time":81.95062877},
{"learn":[0.7585373495],"iteration":510,"passed_time":107.4153621,"remaining_time":81.77020718},
{"learn":[0.7583232546],"iteration":511,"passed_time":107.643707,"remaining_time":81.57374671},
{"learn":[0.7581200429],"iteration":512,"passed_time":107.8960513,"remaining_time":81.39526681},
{"learn":[0.757981029],"iteration":513,"passed_time":108.1565753,"remaining_time":81.22264212},
{"learn":[0.75774841],"iteration":514,"passed_time":108.3872413,"remaining_time":81.02735514},
{"learn":[0.757444127],"iteration":515,"passed_time":108.6345826,"remaining_time":80.84434053},
{"learn":[0.7571831932],"iteration":516,"passed_time":108.8967828,"remaining_time":80.67208476},
{"learn":[0.7570001223],"iteration":517,"passed_time":109.1376855,"remaining_time":80.48377579},
{"learn":[0.7567108832],"iteration":518,"passed_time":109.3744207,"remaining_time":80.29220476},
{"learn":[0.7565262311],"iteration":519,"passed_time":109.6353596,"remaining_time":80.11814737},
{"learn":[0.7563473601],"iteration":520,"passed_time":109.9242968,"remaining_time":79.96412376},
{"learn":[0.7561839228],"iteration":521,"passed_time":110.2288429,"remaining_time":79.82088621},
{"learn":[0.7559710918],"iteration":522,"passed_time":110.4791606,"remaining_time":79.6379418},
{"learn":[0.7558292625],"iteration":523,"passed_time":110.7288371,"remaining_time":79.45428005},
{"learn":[0.7555971645],"iteration":524,"passed_time":110.9707801,"remaining_time":79.2648429},
{"learn":[0.7553867946],"iteration":525,"passed_time":111.2118575,"remaining_time":79.07459071},
{"learn":[0.755174223],"iteration":526,"passed_time":111.4398181,"remaining_time":78.87486176},
{"learn":[0.7549782361],"iteration":527,"passed_time":111.708483,"remaining_time":78.70370391},
{"learn":[0.7547597878],"iteration":528,"passed_time":111.9782477,"remaining_time":78.53294878},
{"learn":[0.7545202379],"iteration":529,"passed_time":112.2260884,"remaining_time":78.34651455},
{"learn":[0.7542679867],"iteration":530,"passed_time":112.490162,"remaining_time":78.17112952},
{"learn":[0.7540465011],"iteration":531,"passed_time":112.7478734,"remaining_time":77.99101018},
{"learn":[0.7538256445],"iteration":532,"passed_time":112.9625567,"remaining_time":77.78097245},
{"learn":[0.7535782535],"iteration":533,"passed_time":113.2534774,"remaining_time":77.62316987},
{"learn":[0.7533469984],"iteration":534,"passed_time":113.5113369,"remaining_time":77.44231397},
{"learn":[0.7529579043],"iteration":535,"passed_time":113.7583709,"remaining_time":77.25381906},
{"learn":[0.7528251371],"iteration":536,"passed_time":113.946609,"remaining_time":77.02536142},
{"learn":[0.7526452028],"iteration":537,"passed_time":114.1970062,"remaining_time":76.8388778},
{"learn":[0.7524718569],"iteration":538,"passed_time":114.4284746,"remaining_time":76.63947928},
{"learn":[0.7522937129],"iteration":539,"passed_time":114.6841997,"remaining_time":76.45613315},
{"learn":[0.7520966625],"iteration":540,"passed_time":114.9222818,"remaining_time":76.26081178},
{"learn":[0.7518356653],"iteration":541,"passed_time":115.1526133,"remaining_time":76.06021322},
{"learn":[0.7516699153],"iteration":542,"passed_time":115.3820037,"remaining_time":75.85888644},
{"learn":[0.7514168531],"iteration":543,"passed_time":115.6239039,"remaining_time":75.665643},
{"learn":[0.7512062554],"iteration":544,"passed_time":115.8652877,"remaining_time":75.47188464},
{"learn":[0.7509900625],"iteration":545,"passed_time":116.1237878,"remaining_time":75.28904922},
{"learn":[0.7508670957],"iteration":546,"passed_time":116.3580527,"remaining_time":75.09029725},
{"learn":[0.7507168672],"iteration":547,"passed_time":116.5745717,"remaining_time":74.88001685},
{"learn":[0.7504578177],"iteration":548,"passed_time":116.8142074,"remaining_time":74.68449328},
{"learn":[0.7502791118],"iteration":549,"passed_time":117.0517103,"remaining_time":74.48745203},
{"learn":[0.7501380207],"iteration":550,"passed_time":117.2958117,"remaining_time":74.29444335},
{"learn":[0.7500016431],"iteration":551,"passed_time":117.4858598,"remaining_time":74.06717249},
{"learn":[0.749749952],"iteration":552,"passed_time":117.7223335,"remaining_time":73.86916768},
{"learn":[0.7495600956],"iteration":553,"passed_time":117.9940572,"remaining_time":73.69303935},
{"learn":[0.7493097426],"iteration":554,"passed_time":118.2220402,"remaining_time":73.48937637},
{"learn":[0.7491455818],"iteration":555,"passed_time":118.4882004,"remaining_time":73.30924627},
{"learn":[0.7489746481],"iteration":556,"passed_time":118.7372695,"remaining_time":73.11828263},
{"learn":[0.7488127519],"iteration":557,"passed_time":118.98885,"remaining_time":72.92865001},
{"learn":[0.7486002033],"iteration":558,"passed_time":119.2221964,"remaining_time":72.7276726},
{"learn":[0.7484710676],"iteration":559,"passed_time":119.4379829,"remaining_time":72.5159182},
{"learn":[0.7483571979],"iteration":560,"passed_time":119.712657,"remaining_time":72.33973389},
{"learn":[0.7481997054],"iteration":561,"passed_time":119.9165397,"remaining_time":72.12062351},
{"learn":[0.7479990988],"iteration":562,"passed_time":120.1892056,"remaining_time":71.94273941},
{"learn":[0.7477680983],"iteration":563,"passed_time":120.4445632,"remaining_time":71.75420786},
{"learn":[0.7475882026],"iteration":564,"passed_time":120.6770221,"remaining_time":71.55186266},
{"learn":[0.7473751351],"iteration":565,"passed_time":120.9287666,"remaining_time":71.36079158},
{"learn":[0.747213347],"iteration":566,"passed_time":121.1641907,"remaining_time":71.15992151},
{"learn":[0.7470851239],"iteration":567,"passed_time":121.4122366,"remaining_time":70.96630733},
{"learn":[0.7469023972],"iteration":568,"passed_time":121.6261379,"remaining_time":70.75263909},
{"learn":[0.7467947321],"iteration":569,"passed_time":121.8923457,"remaining_time":70.56925276},
{"learn":[0.7466429787],"iteration":570,"passed_time":122.1160255,"remaining_time":70.36107251},
{"learn":[0.7464910274],"iteration":571,"passed_time":122.358083,"remaining_time":70.16337627},
{"learn":[0.7463173576],"iteration":572,"passed_time":122.5939449,"remaining_time":69.96198951},
{"learn":[0.7461274746],"iteration":573,"passed_time":122.8408034,"remaining_time":69.76672807},
{"learn":[0.7459088411],"iteration":574,"passed_time":123.0651264,"remaining_time":69.5585497},
{"learn":[0.7456913695],"iteration":575,"passed_time":123.2931765,"remaining_time":69.35241177},
{"learn":[0.7454855588],"iteration":576,"passed_time":123.560082,"remaining_time":69.16794886},
{"learn":[0.7452972557],"iteration":577,"passed_time":123.8256301,"remaining_time":68.98244446},
{"learn":[0.7451555991],"iteration":578,"passed_time":124.0503279,"remaining_time":68.774016},
{"learn":[0.7450100432],"iteration":579,"passed_time":124.3652049,"remaining_time":68.61528544},
{"learn":[0.7448772099],"iteration":580,"passed_time":124.6030219,"remaining_time":68.41370739},
{"learn":[0.7447231758],"iteration":581,"passed_time":124.8672428,"remaining_time":68.22643165},
{"learn":[0.7445402914],"iteration":582,"passed_time":125.1238985,"remaining_time":68.03477844},
{"learn":[0.7443770661],"iteration":583,"passed_time":125.3658401,"remaining_time":67.83494089},
{"learn":[0.7442207964],"iteration":584,"passed_time":125.6146474,"remaining_time":67.6386563},
{"learn":[0.7440925359],"iteration":585,"passed_time":125.8486909,"remaining_time":67.4342815},
{"learn":[0.7439432827],"iteration":586,"passed_time":126.0666047,"remaining_time":67.22120491},
{"learn":[0.7438199722],"iteration":587,"passed_time":126.3505593,"remaining_time":67.04315392},
{"learn":[0.7436108076],"iteration":588,"passed_time":126.582015,"remaining_time":66.83702319},
{"learn":[0.7434159922],"iteration":589,"passed_time":126.8415903,"remaining_time":66.64558134},
{"learn":[0.7432810203],"iteration":590,"passed_time":127.1052201,"remaining_time":66.45602876},
{"learn":[0.7430000307],"iteration":591,"passed_time":127.3517556,"remaining_time":66.2573323},
{"learn":[0.7427767383],"iteration":592,"passed_time":127.613442,"remaining_time":66.06631818},
{"learn":[0.7426085554],"iteration":593,"passed_time":127.8391364,"remaining_time":65.85652483},
{"learn":[0.7424884614],"iteration":594,"passed_time":128.114982,"remaining_time":65.67238573},
{"learn":[0.7423652581],"iteration":595,"passed_time":128.3503553,"remaining_time":65.46729534},
{"learn":[0.7422054702],"iteration":596,"passed_time":128.5933712,"remaining_time":65.26598234},
{"learn":[0.7420342352],"iteration":597,"passed_time":128.8545078,"remaining_time":65.07368121},
{"learn":[0.7418931284],"iteration":598,"passed_time":129.0820112,"remaining_time":64.86424937},
{"learn":[0.7416821114],"iteration":599,"passed_time":129.3173867,"remaining_time":64.65869335},
{"learn":[0.7415055946],"iteration":600,"passed_time":129.5709598,"remaining_time":64.4620915},
{"learn":[0.7413855539],"iteration":601,"passed_time":129.8217641,"remaining_time":64.26392973},
{"learn":[0.7412082044],"iteration":602,"passed_time":130.0788492,"remaining_time":64.06868691},
{"learn":[0.7410345142],"iteration":603,"passed_time":130.3060918,"remaining_time":63.85861453},
{"learn":[0.7409142989],"iteration":604,"passed_time":130.5538648,"remaining_time":63.65849607},
{"learn":[0.7407798474],"iteration":605,"passed_time":130.7922623,"remaining_time":63.45367179},
{"learn":[0.7405796453],"iteration":606,"passed_time":131.0338423,"remaining_time":63.25027314},
{"learn":[0.7403945999],"iteration":607,"passed_time":131.280649,"remaining_time":63.04925906},
{"learn":[0.7402552544],"iteration":608,"passed_time":131.5139744,"remaining_time":62.84165279},
{"learn":[0.7400965974],"iteration":609,"passed_time":131.7532569,"remaining_time":62.63679425},
{"learn":[0.7399034763],"iteration":610,"passed_time":131.9820326,"remaining_time":62.4268534},
{"learn":[0.7397272645],"iteration":611,"passed_time":132.2262921,"remaining_time":62.22413746},
{"learn":[0.7395574169],"iteration":612,"passed_time":132.4538767,"remaining_time":62.01347897},
{"learn":[0.7393364214],"iteration":613,"passed_time":132.716702,"remaining_time":61.81918042},
{"learn":[0.7391843244],"iteration":614,"passed_time":132.9965923,"remaining_time":61.63256717},
{"learn":[0.7390664929],"iteration":615,"passed_time":133.304028,"remaining_time":61.45835059},
{"learn":[0.7388397752],"iteration":616,"passed_time":133.5240403,"remaining_time":61.24360359},
{"learn":[0.7386366823],"iteration":617,"passed_time":133.8055327,"remaining_time":61.05689355},
{"learn":[0.7384439097],"iteration":618,"passed_time":134.038574,"remaining_time":60.84788253},
{"learn":[0.7382528411],"iteration":619,"passed_time":134.2823084,"remaining_time":60.64362314},
{"learn":[0.7380012289],"iteration":620,"passed_time":134.5483258,"remaining_time":60.4492478},
{"learn":[0.7378843753],"iteration":621,"passed_time":134.814356,"remaining_time":60.25464788},
{"learn":[0.7377522893],"iteration":622,"passed_time":135.0694452,"remaining_time":60.05495395},
{"learn":[0.7376140293],"iteration":623,"passed_time":135.3068912,"remaining_time":59.84727879},
{"learn":[0.7374496358],"iteration":624,"passed_time":135.5290949,"remaining_time":59.63280176},
{"learn":[0.7373478801],"iteration":625,"passed_time":135.779162,"remaining_time":59.43049583},
{"learn":[0.7372203631],"iteration":626,"passed_time":136.0268645,"remaining_time":59.22700798},
{"learn":[0.7371442015],"iteration":627,"passed_time":136.2756187,"remaining_time":59.02383484},
{"learn":[0.7370178176],"iteration":628,"passed_time":136.5248123,"remaining_time":58.82070609},
{"learn":[0.7369167508],"iteration":629,"passed_time":136.7384888,"remaining_time":58.60220948},
{"learn":[0.7367002526],"iteration":630,"passed_time":136.9743749,"remaining_time":58.39319629},
{"learn":[0.7364585489],"iteration":631,"passed_time":137.2233427,"remaining_time":58.18964534},
{"learn":[0.7363005049],"iteration":632,"passed_time":137.4663638,"remaining_time":57.98344256},
{"learn":[0.7361901089],"iteration":633,"passed_time":137.739962,"remaining_time":57.78995251},
{"learn":[0.7360416151],"iteration":634,"passed_time":137.9856459,"remaining_time":57.58456087},
{"learn":[0.7358939663],"iteration":635,"passed_time":138.2407667,"remaining_time":57.38295975},
{"learn":[0.7357903952],"iteration":636,"passed_time":138.4735443,"remaining_time":57.17196568},
{"learn":[0.735641796],"iteration":637,"passed_time":138.702122,"remaining_time":56.95917863},
{"learn":[0.735545466],"iteration":638,"passed_time":138.9476625,"remaining_time":56.75327058},
{"learn":[0.7354393982],"iteration":639,"passed_time":139.1930929,"remaining_time":56.54719399},
{"learn":[0.7353304415],"iteration":640,"passed_time":139.413332,"remaining_time":56.33081588},
{"learn":[0.7349786407],"iteration":641,"passed_time":139.6192276,"remaining_time":56.10866158},
{"learn":[0.7347694398],"iteration":642,"passed_time":139.8310979,"remaining_time":55.88894582},
{"learn":[0.7345146774],"iteration":643,"passed_time":140.079266,"remaining_time":55.68368338},
{"learn":[0.7343114568],"iteration":644,"passed_time":140.3078811,"remaining_time":55.47055766},
{"learn":[0.7341597526],"iteration":645,"passed_time":140.49298,"remaining_time":55.24027387},
{"learn":[0.7339636545],"iteration":646,"passed_time":140.7457038,"remaining_time":55.03657351},
{"learn":[0.7338511654],"iteration":647,"passed_time":140.9854486,"remaining_time":54.82767445},
{"learn":[0.733628885],"iteration":648,"passed_time":141.2015464,"remaining_time":54.6095349},
{"learn":[0.7335238523],"iteration":649,"passed_time":141.4689702,"remaining_time":54.41114238},
{"learn":[0.7334147336],"iteration":650,"passed_time":141.7200042,"remaining_time":54.20626887},
{"learn":[0.7332392436],"iteration":651,"passed_time":141.953356,"remaining_time":53.99452804},
{"learn":[0.733092244],"iteration":652,"passed_time":142.1749194,"remaining_time":53.77826202},
{"learn":[0.7329613788],"iteration":653,"passed_time":142.4378702,"remaining_time":53.57754751},
{"learn":[0.7328419888],"iteration":654,"passed_time":142.6934918,"remaining_time":53.37390151},
{"learn":[0.73267226],"iteration":655,"passed_time":142.9548804,"remaining_time":53.17224209},
{"learn":[0.7324942058],"iteration":656,"passed_time":143.1915284,"remaining_time":52.96125022},
{"learn":[0.7323145053],"iteration":657,"passed_time":143.3771908,"remaining_time":52.73142885},
{"learn":[0.732200386],"iteration":658,"passed_time":143.5619312,"remaining_time":52.50140428},
{"learn":[0.7321268342],"iteration":659,"passed_time":143.7302967,"remaining_time":52.26556243},
{"learn":[0.7318886342],"iteration":660,"passed_time":143.889353,"remaining_time":52.02655879},
{"learn":[0.7317659272],"iteration":661,"passed_time":144.0489512,"remaining_time":51.78799152},
{"learn":[0.7315815756],"iteration":662,"passed_time":144.1915159,"remaining_time":51.54357356},
{"learn":[0.7314538097],"iteration":663,"passed_time":144.3292602,"remaining_time":51.2977491},
{"learn":[0.7313224159],"iteration":664,"passed_time":144.4204853,"remaining_time":51.03581058},
{"learn":[0.7311583191],"iteration":665,"passed_time":144.5189236,"remaining_time":50.77691911},
{"learn":[0.7310294985],"iteration":666,"passed_time":144.6184467,"remaining_time":50.51888768},
{"learn":[0.7308958984],"iteration":667,"passed_time":144.7408086,"remaining_time":50.26926288},
{"learn":[0.7307709556],"iteration":668,"passed_time":144.8396295,"remaining_time":50.01189001},
{"learn":[0.730653809],"iteration":669,"passed_time":144.9352629,"remaining_time":49.75389623},
{"learn":[0.7305146264],"iteration":670,"passed_time":145.0339069,"remaining_time":49.49741383},
{"learn":[0.7303664731],"iteration":671,"passed_time":145.1339396,"remaining_time":49.24187238},
{"learn":[0.730119992],"iteration":672,"passed_time":145.2263986,"remaining_time":48.98423844},
{"learn":[0.7300169291],"iteration":673,"passed_time":145.3218764,"remaining_time":48.72810693},
{"learn":[0.729862905],"iteration":674,"passed_time":145.4149091,"remaining_time":48.47163636},
{"learn":[0.7297609206],"iteration":675,"passed_time":145.4968621,"remaining_time":48.21197796},
{"learn":[0.7295593081],"iteration":676,"passed_time":145.5891688,"remaining_time":47.95625501},
{"learn":[0.7294280271],"iteration":677,"passed_time":145.6844288,"remaining_time":47.7019811},
{"learn":[0.7292913473],"iteration":678,"passed_time":145.7705301,"remaining_time":47.44519462},
{"learn":[0.7292041484],"iteration":679,"passed_time":145.8614667,"remaining_time":47.19047453},
{"learn":[0.7290463281],"iteration":680,"passed_time":146.1337729,"remaining_time":46.99456133},
{"learn":[0.7289010746],"iteration":681,"passed_time":146.3583545,"remaining_time":46.78316903},
{"learn":[0.7287396234],"iteration":682,"passed_time":146.6098168,"remaining_time":46.58027853},
{"learn":[0.7286358541],"iteration":683,"passed_time":146.836928,"remaining_time":46.3695562},
{"learn":[0.7284825957],"iteration":684,"passed_time":147.0752618,"remaining_time":46.16230846},
{"learn":[0.7283853802],"iteration":685,"passed_time":147.3157477,"remaining_time":45.95564143},
{"learn":[0.728262066],"iteration":686,"passed_time":147.5602414,"remaining_time":45.75011853},
{"learn":[0.7281155609],"iteration":687,"passed_time":147.7999722,"remaining_time":45.5430147},
{"learn":[0.72797514],"iteration":688,"passed_time":148.0131673,"remaining_time":45.32768983},
{"learn":[0.72783128],"iteration":689,"passed_time":148.2823943,"remaining_time":45.12942436},
{"learn":[0.7276779231],"iteration":690,"passed_time":148.5395422,"remaining_time":44.92730003},
{"learn":[0.7274255825],"iteration":691,"passed_time":148.8254788,"remaining_time":44.73366991},
{"learn":[0.7272787305],"iteration":692,"passed_time":149.0950418,"remaining_time":44.5348826},
{"learn":[0.7271280093],"iteration":693,"passed_time":149.3321075,"remaining_time":44.32624516},
{"learn":[0.7269690719],"iteration":694,"passed_time":149.5682129,"remaining_time":44.11724264},
{"learn":[0.7268183256],"iteration":695,"passed_time":149.8402164,"remaining_time":43.91868413},
{"learn":[0.7266381334],"iteration":696,"passed_time":150.0724813,"remaining_time":43.70834105},
{"learn":[0.7265145198],"iteration":697,"passed_time":150.3293381,"remaining_time":43.50505201},
{"learn":[0.7263613404],"iteration":698,"passed_time":150.5826241,"remaining_time":43.30058291},
{"learn":[0.7262768058],"iteration":699,"passed_time":150.8300901,"remaining_time":43.09431145},
{"learn":[0.7261716993],"iteration":700,"passed_time":151.0647149,"remaining_time":42.88427712},
{"learn":[0.7260320944],"iteration":701,"passed_time":151.2986396,"remaining_time":42.67397528},
{"learn":[0.7258386079],"iteration":702,"passed_time":151.5768626,"remaining_time":42.4760198},
{"learn":[0.7257330403],"iteration":703,"passed_time":151.8108231,"remaining_time":42.26551325},
{"learn":[0.7256134935],"iteration":704,"passed_time":152.0252049,"remaining_time":42.04952477},
{"learn":[0.7254332044],"iteration":705,"passed_time":152.2910687,"remaining_time":41.84768743},
{"learn":[0.7252675171],"iteration":706,"passed_time":152.5373516,"remaining_time":41.64032371},
{"learn":[0.725157543],"iteration":707,"passed_time":152.7710892,"remaining_time":41.42944793},
{"learn":[0.7250520661],"iteration":708,"passed_time":153.0030914,"remaining_time":41.21804013},
{"learn":[0.7248716243],"iteration":709,"passed_time":153.2418416,"remaining_time":41.00838015},
{"learn":[0.7247601355],"iteration":710,"passed_time":153.4715377,"remaining_time":40.79623154},
{"learn":[0.7245927519],"iteration":711,"passed_time":153.7122322,"remaining_time":40.58693773},
{"learn":[0.7244411874],"iteration":712,"passed_time":153.9178412,"remaining_time":40.36835385},
{"learn":[0.724275582],"iteration":713,"passed_time":154.1425139,"remaining_time":40.15477254},
{"learn":[0.7240715941],"iteration":714,"passed_time":154.3497478,"remaining_time":39.93664803},
{"learn":[0.7239401675],"iteration":715,"passed_time":154.6073777,"remaining_time":39.73150487},
{"learn":[0.7238188527],"iteration":716,"passed_time":154.8572097,"remaining_time":39.52422508},
{"learn":[0.7236097108],"iteration":717,"passed_time":155.1054631,"remaining_time":39.31642658},
{"learn":[0.723511009],"iteration":718,"passed_time":155.3407004,"remaining_time":39.1052389},
{"learn":[0.7234482541],"iteration":719,"passed_time":155.5642965,"remaining_time":38.89107412},
{"learn":[0.7232819317],"iteration":720,"passed_time":155.8048999,"remaining_time":38.68110552},
{"learn":[0.7231484559],"iteration":721,"passed_time":156.0087576,"remaining_time":38.46199286},
{"learn":[0.723031867],"iteration":722,"passed_time":156.2544933,"remaining_time":38.2531747},
{"learn":[0.7229014336],"iteration":723,"passed_time":156.496681,"remaining_time":38.04339207},
{"learn":[0.7227722806],"iteration":724,"passed_time":156.7330774,"remaining_time":37.83212212},
{"learn":[0.7226411467],"iteration":725,"passed_time":156.9689723,"remaining_time":37.62066278},
{"learn":[0.7224774839],"iteration":726,"passed_time":157.2009073,"remaining_time":37.4081939},
{"learn":[0.7223603885],"iteration":727,"passed_time":157.4393472,"remaining_time":37.19720841},
{"learn":[0.7222325163],"iteration":728,"passed_time":157.693335,"remaining_time":36.98979464},
{"learn":[0.7221352448],"iteration":729,"passed_time":157.9110129,"remaining_time":36.77379752},
{"learn":[0.7219228596],"iteration":730,"passed_time":158.171538,"remaining_time":36.56770166},
{"learn":[0.7218330921],"iteration":731,"passed_time":158.4224085,"remaining_time":36.3592413},
{"learn":[0.7216864264],"iteration":732,"passed_time":158.6689477,"remaining_time":36.14967839},
{"learn":[0.721619803],"iteration":733,"passed_time":158.9089043,"remaining_time":35.93852604},
{"learn":[0.7214902208],"iteration":734,"passed_time":159.1575557,"remaining_time":35.72924721},
{"learn":[0.7213584963],"iteration":735,"passed_time":159.4156651,"remaining_time":35.52196885},
{"learn":[0.7212465844],"iteration":736,"passed_time":159.6288298,"remaining_time":35.30461229},
{"learn":[0.7211729526],"iteration":737,"passed_time":159.8342285,"remaining_time":35.08556235},
{"learn":[0.7210202963],"iteration":738,"passed_time":160.083892,"remaining_time":34.87619297},
{"learn":[0.7209073395],"iteration":739,"passed_time":160.3154417,"remaining_time":34.66279821},
{"learn":[0.7208004696],"iteration":740,"passed_time":160.5150812,"remaining_time":34.4425073},
{"learn":[0.7206976178],"iteration":741,"passed_time":160.6391475,"remaining_time":34.20617966},
{"learn":[0.7205948302],"iteration":742,"passed_time":160.7316277,"remaining_time":33.96347988},
{"learn":[0.7205213486],"iteration":743,"passed_time":160.8266112,"remaining_time":33.7217088},
{"learn":[0.7204279017],"iteration":744,"passed_time":160.9304659,"remaining_time":33.48217748},
{"learn":[0.7202994842],"iteration":745,"passed_time":161.0089315,"remaining_time":33.2377687},
{"learn":[0.7200692559],"iteration":746,"passed_time":161.0916636,"remaining_time":32.99467808},
{"learn":[0.7199568798],"iteration":747,"passed_time":161.1874914,"remaining_time":32.75467739},
{"learn":[0.7198946439],"iteration":748,"passed_time":161.2815557,"remaining_time":32.51470615},
{"learn":[0.7197795447],"iteration":749,"passed_time":161.3674417,"remaining_time":32.27348833},
{"learn":[0.7196782931],"iteration":750,"passed_time":161.4496657,"remaining_time":32.03195764},
{"learn":[0.7196020204],"iteration":751,"passed_time":161.5432707,"remaining_time":31.79309052},
{"learn":[0.7194834316],"iteration":752,"passed_time":161.6383984,"remaining_time":31.55490646},
{"learn":[0.7193447487],"iteration":753,"passed_time":161.7373371,"remaining_time":31.31783981},
{"learn":[0.7192505694],"iteration":754,"passed_time":161.8358373,"remaining_time":31.08105485},
{"learn":[0.7190998183],"iteration":755,"passed_time":161.9333091,"remaining_time":30.84443982},
{"learn":[0.7189606163],"iteration":756,"passed_time":162.0347946,"remaining_time":30.60895062},
{"learn":[0.7188159246],"iteration":757,"passed_time":162.1315701,"remaining_time":30.37293265},
{"learn":[0.7186832409],"iteration":758,"passed_time":162.2294531,"remaining_time":30.13748734},
{"learn":[0.7184971604],"iteration":759,"passed_time":162.324421,"remaining_time":29.90186702},
{"learn":[0.7184035602],"iteration":760,"passed_time":162.4213352,"remaining_time":29.66697187},
{"learn":[0.7182817073],"iteration":761,"passed_time":162.5200034,"remaining_time":29.43275652},
{"learn":[0.7181831755],"iteration":762,"passed_time":162.6164558,"remaining_time":29.19849862},
{"learn":[0.7181103157],"iteration":763,"passed_time":162.7098628,"remaining_time":28.96405935},
{"learn":[0.7180280137],"iteration":764,"passed_time":162.8121473,"remaining_time":28.73155541},
{"learn":[0.7179338845],"iteration":765,"passed_time":162.9111939,"remaining_time":28.49882503},
{"learn":[0.717638859],"iteration":766,"passed_time":163.0119228,"remaining_time":28.26673497},
{"learn":[0.7174887019],"iteration":767,"passed_time":163.1191164,"remaining_time":28.03609814},
{"learn":[0.7173864936],"iteration":768,"passed_time":163.2200732,"remaining_time":27.80471988},
{"learn":[0.7173049045],"iteration":769,"passed_time":163.3143246,"remaining_time":27.5725483},
{"learn":[0.7171399259],"iteration":770,"passed_time":163.4103481,"remaining_time":27.34103101},
{"learn":[0.7170294943],"iteration":771,"passed_time":163.5041366,"remaining_time":27.10949416},
{"learn":[0.7167993627],"iteration":772,"passed_time":163.5983149,"remaining_time":26.87837773},
{"learn":[0.7166749148],"iteration":773,"passed_time":163.6913261,"remaining_time":26.64742518},
{"learn":[0.7165712709],"iteration":774,"passed_time":163.7863744,"remaining_time":26.41715717},
{"learn":[0.7164237064],"iteration":775,"passed_time":163.882015,"remaining_time":26.1873323},
{"learn":[0.716356964],"iteration":776,"passed_time":163.9673109,"remaining_time":25.95621524},
{"learn":[0.7162518917],"iteration":777,"passed_time":164.0385069,"remaining_time":25.723262},
{"learn":[0.7161510616],"iteration":778,"passed_time":164.1263772,"remaining_time":25.49331405},
{"learn":[0.7160071248],"iteration":779,"passed_time":164.2157808,"remaining_time":25.26396628},
{"learn":[0.7158547553],"iteration":780,"passed_time":164.3034324,"remaining_time":25.03470994},
{"learn":[0.7157949467],"iteration":781,"passed_time":164.3749538,"remaining_time":24.80338178},
{"learn":[0.7157296913],"iteration":782,"passed_time":164.4677281,"remaining_time":24.57563753},
{"learn":[0.7156150967],"iteration":783,"passed_time":164.5664193,"remaining_time":24.34911307},
{"learn":[0.715401833],"iteration":784,"passed_time":164.6637683,"remaining_time":24.12271765},
{"learn":[0.7153091735],"iteration":785,"passed_time":164.7635433,"remaining_time":23.89700246},
{"learn":[0.7152279737],"iteration":786,"passed_time":164.8600274,"remaining_time":23.67113481},
{"learn":[0.7151360705],"iteration":787,"passed_time":164.9535707,"remaining_time":23.44517756},
{"learn":[0.7150362009],"iteration":788,"passed_time":165.0556535,"remaining_time":23.22075734},
{"learn":[0.7148589744],"iteration":789,"passed_time":165.1945804,"remaining_time":23.00177702},
{"learn":[0.7147731402],"iteration":790,"passed_time":165.264354,"remaining_time":22.77346977},
{"learn":[0.71471281],"iteration":791,"passed_time":165.336059,"remaining_time":22.54582623},
{"learn":[0.7146495551],"iteration":792,"passed_time":165.4119889,"remaining_time":22.31914605},
{"learn":[0.7144735339],"iteration":793,"passed_time":165.4829061,"remaining_time":22.09217639},
{"learn":[0.7143746508],"iteration":794,"passed_time":165.5519006,"remaining_time":21.86534537},
{"learn":[0.7142656426],"iteration":795,"passed_time":165.6201006,"remaining_time":21.63880712},
{"learn":[0.7141802516],"iteration":796,"passed_time":165.6894098,"remaining_time":21.41280955},
{"learn":[0.7140110467],"iteration":797,"passed_time":165.765724,"remaining_time":21.18810007},
{"learn":[0.7138640543],"iteration":798,"passed_time":165.8404264,"remaining_time":20.96355829},
{"learn":[0.7137547615],"iteration":799,"passed_time":165.9152356,"remaining_time":20.73940445},
{"learn":[0.7136540368],"iteration":800,"passed_time":165.9942492,"remaining_time":20.51614316},
{"learn":[0.7135759513],"iteration":801,"passed_time":166.0714175,"remaining_time":20.2930161},
{"learn":[0.7134433932],"iteration":802,"passed_time":166.1392342,"remaining_time":20.06912294},
{"learn":[0.7132700581],"iteration":803,"passed_time":166.2130122,"remaining_time":19.84632982},
{"learn":[0.7132114733],"iteration":804,"passed_time":166.2866136,"remaining_time":19.62388607},
{"learn":[0.7131188085],"iteration":805,"passed_time":166.3594957,"remaining_time":19.40172779},
{"learn":[0.7129982265],"iteration":806,"passed_time":166.4289523,"remaining_time":19.17954469},
{"learn":[0.7128902736],"iteration":807,"passed_time":166.4969227,"remaining_time":18.95757041},
{"learn":[0.712701476],"iteration":808,"passed_time":166.572454,"remaining_time":18.73682733},
{"learn":[0.7125779172],"iteration":809,"passed_time":166.6504822,"remaining_time":18.51672024},
{"learn":[0.7124746987],"iteration":810,"passed_time":166.7256551,"remaining_time":18.29665019},
{"learn":[0.7123901083],"iteration":811,"passed_time":166.7952179,"remaining_time":18.07632904},
{"learn":[0.7122943208],"iteration":812,"passed_time":166.8637889,"remaining_time":17.85627261},
{"learn":[0.7121835433],"iteration":813,"passed_time":166.931922,"remaining_time":17.63654213},
{"learn":[0.7120874953],"iteration":814,"passed_time":167.0064904,"remaining_time":17.41785483},
{"learn":[0.7120383509],"iteration":815,"passed_time":167.0804362,"remaining_time":17.19945666},
{"learn":[0.7119514216],"iteration":816,"passed_time":167.1505698,"remaining_time":16.98102484},
{"learn":[0.7118513504],"iteration":817,"passed_time":167.2206103,"remaining_time":16.76294627},
{"learn":[0.7117096335],"iteration":818,"passed_time":167.2934434,"remaining_time":16.54550539},
{"learn":[0.711616885],"iteration":819,"passed_time":167.3700736,"remaining_time":16.32878767},
{"learn":[0.7115180753],"iteration":820,"passed_time":167.4450514,"remaining_time":16.11225221},
{"learn":[0.7114275946],"iteration":821,"passed_time":167.516336,"remaining_time":15.89571071},
{"learn":[0.7113457315],"iteration":822,"passed_time":167.5829834,"remaining_time":15.67908836},
{"learn":[0.71121005],"iteration":823,"passed_time":167.6540205,"remaining_time":15.4632349},
{"learn":[0.7110463824],"iteration":824,"passed_time":167.7267388,"remaining_time":15.24788534},
{"learn":[0.7109293008],"iteration":825,"passed_time":167.8006514,"remaining_time":15.03298814},
{"learn":[0.7108033937],"iteration":826,"passed_time":167.8702037,"remaining_time":14.818047},
{"learn":[0.7107454861],"iteration":827,"passed_time":167.9400886,"remaining_time":14.60348597},
{"learn":[0.7106299281],"iteration":828,"passed_time":168.0146838,"remaining_time":14.38967739},
{"learn":[0.7105460382],"iteration":829,"passed_time":168.0867947,"remaining_time":14.17599474},
{"learn":[0.7104829462],"iteration":830,"passed_time":168.1566153,"remaining_time":13.96246264},
{"learn":[0.7104170705],"iteration":831,"passed_time":168.2210528,"remaining_time":13.74883605},
{"learn":[0.7103357279],"iteration":832,"passed_time":168.2855653,"remaining_time":13.53557368},
{"learn":[0.710288533],"iteration":833,"passed_time":168.3617163,"remaining_time":13.32358906},
{"learn":[0.7101988406],"iteration":834,"passed_time":168.4349334,"remaining_time":13.1117014},
{"learn":[0.7100558338],"iteration":835,"passed_time":168.5071166,"remaining_time":12.90006634},
{"learn":[0.7100110725],"iteration":836,"passed_time":168.5785202,"remaining_time":12.68870582},
{"learn":[0.7099166991],"iteration":837,"passed_time":168.6559574,"remaining_time":12.47812573},
{"learn":[0.7098236783],"iteration":838,"passed_time":168.7242452,"remaining_time":12.2671978},
{"learn":[0.7097113033],"iteration":839,"passed_time":168.792935,"remaining_time":12.05663821},
{"learn":[0.7095863926],"iteration":840,"passed_time":168.8673948,"remaining_time":11.8468208},
{"learn":[0.7094962252],"iteration":841,"passed_time":168.9432006,"remaining_time":11.63741762},
{"learn":[0.7093787035],"iteration":842,"passed_time":169.0113054,"remaining_time":11.42781069},
{"learn":[0.7092777402],"iteration":843,"passed_time":169.0811678,"remaining_time":11.21865569},
{"learn":[0.7091586633],"iteration":844,"passed_time":169.1494756,"remaining_time":11.00972918},
{"learn":[0.7090324543],"iteration":845,"passed_time":169.2272216,"remaining_time":10.80173755},
{"learn":[0.7088825747],"iteration":846,"passed_time":169.3009301,"remaining_time":10.59380082},
{"learn":[0.7088038789],"iteration":847,"passed_time":169.3704506,"remaining_time":10.38592386},
{"learn":[0.7087134085],"iteration":848,"passed_time":169.4383133,"remaining_time":10.17827324},
{"learn":[0.7085993459],"iteration":849,"passed_time":169.5083515,"remaining_time":9.971079502},
{"learn":[0.7085109129],"iteration":850,"passed_time":169.5795496,"remaining_time":9.76427489},
{"learn":[0.7084620811],"iteration":851,"passed_time":169.6549251,"remaining_time":9.55802395},
{"learn":[0.7083229778],"iteration":852,"passed_time":169.7164292,"remaining_time":9.351315562},
{"learn":[0.7081955573],"iteration":853,"passed_time":169.778042,"remaining_time":9.144953083},
{"learn":[0.7081089481],"iteration":854,"passed_time":169.8506289,"remaining_time":8.939506782},
{"learn":[0.7079615848],"iteration":855,"passed_time":169.926684,"remaining_time":8.734549177},
{"learn":[0.7078780974],"iteration":856,"passed_time":169.9955487,"remaining_time":8.529531617},
{"learn":[0.7077694604],"iteration":857,"passed_time":170.0688281,"remaining_time":8.325047528},
{"learn":[0.7076706683],"iteration":858,"passed_time":170.1462256,"remaining_time":8.121065485},
{"learn":[0.707615512],"iteration":859,"passed_time":170.2148384,"remaining_time":7.91696923},
{"learn":[0.7075087328],"iteration":860,"passed_time":170.2824698,"remaining_time":7.713143229},
{"learn":[0.7074263369],"iteration":861,"passed_time":170.356895,"remaining_time":7.509932726},
{"learn":[0.7073468729],"iteration":862,"passed_time":170.4324674,"remaining_time":7.307069866},
{"learn":[0.7072613002],"iteration":863,"passed_time":170.5007946,"remaining_time":7.104199773},
{"learn":[0.7071620973],"iteration":864,"passed_time":170.5733058,"remaining_time":6.901810063},
{"learn":[0.7070164436],"iteration":865,"passed_time":170.6491601,"remaining_time":6.699851551},
{"learn":[0.7069059361],"iteration":866,"passed_time":170.7205438,"remaining_time":6.498013778},
{"learn":[0.7068530599],"iteration":867,"passed_time":170.7870346,"remaining_time":6.296296205},
{"learn":[0.7067581663],"iteration":868,"passed_time":170.8589556,"remaining_time":6.095083573},
{"learn":[0.706698824],"iteration":869,"passed_time":170.9307968,"remaining_time":5.894165408},
{"learn":[0.7065927555],"iteration":870,"passed_time":171.0085389,"remaining_time":5.693740102},
{"learn":[0.7064575205],"iteration":871,"passed_time":171.0795632,"remaining_time":5.493380468},
{"learn":[0.7063490805],"iteration":872,"passed_time":171.1526597,"remaining_time":5.293381226},
{"learn":[0.7062389252],"iteration":873,"passed_time":171.224257,"remaining_time":5.093627782},
{"learn":[0.7061541567],"iteration":874,"passed_time":171.3064388,"remaining_time":4.894469679},
{"learn":[0.7060566785],"iteration":875,"passed_time":171.3743955,"remaining_time":4.695188917},
{"learn":[0.7058918154],"iteration":876,"passed_time":171.4504088,"remaining_time":4.496418931},
{"learn":[0.7057574499],"iteration":877,"passed_time":171.5311827,"remaining_time":4.298047858},
{"learn":[0.7056723138],"iteration":878,"passed_time":171.6134356,"remaining_time":4.099979691},
{"learn":[0.7055795913],"iteration":879,"passed_time":171.6920186,"remaining_time":3.902091332},
{"learn":[0.7055063132],"iteration":880,"passed_time":171.7694959,"remaining_time":3.704449967},
{"learn":[0.7054081426],"iteration":881,"passed_time":171.8392474,"remaining_time":3.506923415},
{"learn":[0.7052968334],"iteration":882,"passed_time":171.9677968,"remaining_time":3.310818285},
{"learn":[0.7051895808],"iteration":883,"passed_time":172.0415686,"remaining_time":3.113874545},
{"learn":[0.705040391],"iteration":884,"passed_time":172.1137298,"remaining_time":2.917181861},
{"learn":[0.7049328202],"iteration":885,"passed_time":172.1889114,"remaining_time":2.720818013},
{"learn":[0.704887032],"iteration":886,"passed_time":172.2570624,"remaining_time":2.524624364},
{"learn":[0.7047837486],"iteration":887,"passed_time":172.3283749,"remaining_time":2.328761823},
{"learn":[0.7047098091],"iteration":888,"passed_time":172.4013105,"remaining_time":2.133199567},
{"learn":[0.7045802082],"iteration":889,"passed_time":172.471124,"remaining_time":1.937877797},
{"learn":[0.7044769239],"iteration":890,"passed_time":172.53732,"remaining_time":1.742801212},
{"learn":[0.7043936138],"iteration":891,"passed_time":172.6031689,"remaining_time":1.548010484},
{"learn":[0.7043165935],"iteration":892,"passed_time":172.6708253,"remaining_time":1.353522707},
{"learn":[0.7042108111],"iteration":893,"passed_time":172.7470246,"remaining_time":1.159376004},
{"learn":[0.7041621725],"iteration":894,"passed_time":172.8187445,"remaining_time":0.9654678462},
{"learn":[0.704085282],"iteration":895,"passed_time":172.8892695,"remaining_time":0.7718270959},
{"learn":[0.7039965903],"iteration":896,"passed_time":172.9584096,"remaining_time":0.5784562193},
{"learn":[0.7039067547],"iteration":897,"passed_time":173.0174015,"remaining_time":0.3853394242},
{"learn":[0.703822533],"iteration":898,"passed_time":173.0889731,"remaining_time":0.192535009},
{"learn":[0.7036723033],"iteration":899,"passed_time":173.1618687,"remaining_time":0}
]}